setup.py
formskit/__init__.py
formskit/converters.py
formskit/errors.py
formskit/field.py
formskit/form.py
formskit/formvalidators.py
formskit/translation.py
formskit/tree_form.py
formskit/validators.py
formskit.egg-info/PKG-INFO
formskit.egg-info/SOURCES.txt
formskit.egg-info/dependency_links.txt
formskit.egg-info/top_level.txt
formskit/tests/__init__.py
formskit/tests/base.py
formskit/tests/test_convert.py
formskit/tests/test_errors.py
formskit/tests/test_field.py
formskit/tests/test_form.py
formskit/tests/test_formvalidators.py
formskit/tests/test_translation.py
formskit/tests/test_treeform.py
formskit/tests/test_validators.py