Metadata-Version: 1.0
Name: formskit
Version: 0.5.4.10
Summary: Simple forms validation.
Home-page: https://github.com/socek/formskit/
Author: ['Dominik "Socek" Długajczy']
Author-email: ['msocek@gmail.com']
License: UNKNOWN
Platform: UNKNOWN
